experiencemaker/__init__.py
experiencemaker/app.py
experiencemaker/mcp_server.py
experiencemaker/config/__init__.py
experiencemaker/config/config_parser.py
experiencemaker/config/default_config.yaml
experiencemaker/config/mock_config.yaml
experiencemaker/config/simple_config.yaml
experiencemaker/embedding_model/__init__.py
experiencemaker/embedding_model/base_embedding_model.py
experiencemaker/embedding_model/openai_compatible_embedding_model.py
experiencemaker/enumeration/__init__.py
experiencemaker/enumeration/agent_state.py
experiencemaker/enumeration/chunk_enum.py
experiencemaker/enumeration/http_enum.py
experiencemaker/enumeration/role.py
experiencemaker/llm/__init__.py
experiencemaker/llm/base_llm.py
experiencemaker/llm/openai_compatible_llm.py
experiencemaker/op/__init__.py
experiencemaker/op/base_op.py
experiencemaker/op/mock_op.py
experiencemaker/op/prompt_mixin.py
experiencemaker/op/react/__init__.py
experiencemaker/op/react/react_v1_op.py
experiencemaker/op/react/react_v1_prompt.yaml
experiencemaker/op/retriever/__init__.py
experiencemaker/op/retriever/build_query_op.py
experiencemaker/op/retriever/build_query_prompt.yaml
experiencemaker/op/retriever/merge_experience_op.py
experiencemaker/op/retriever/rerank_experience_op.py
experiencemaker/op/retriever/rerank_experience_prompt.yaml
experiencemaker/op/retriever/rewrite_experience_op.py
experiencemaker/op/retriever/rewrite_experience_prompt.yaml
experiencemaker/op/summarizer/__init__.py
experiencemaker/op/summarizer/comparative_extraction_op.py
experiencemaker/op/summarizer/comparative_extraction_prompt.yaml
experiencemaker/op/summarizer/experience_deduplication_op.py
experiencemaker/op/summarizer/experience_validation_op.py
experiencemaker/op/summarizer/experience_validation_prompt.yaml
experiencemaker/op/summarizer/failure_extraction_op.py
experiencemaker/op/summarizer/failure_extraction_prompt.yaml
experiencemaker/op/summarizer/simple_comparative_summary_op.py
experiencemaker-0.1.1.dist-info/licenses/LICENSE
experiencemaker-0.1.1.dist-info/METADATA
experiencemaker-0.1.1.dist-info/WHEEL
experiencemaker-0.1.1.dist-info/entry_points.txt
experiencemaker-0.1.1.dist-info/top_level.txt
experiencemaker-0.1.1.dist-info/RECORD
