Metadata-Version: 2.4
Name: ExperienceMaker
Version: 0.1.1
Summary: make experience from trajectory
Author-email: experiencemaker team <experiencemaker@alibaba-inc.com>
License:                                  Apache License
Classifier: Programming Language :: Python :: 3
Classifier: License :: OSI Approved :: Apache Software License
Classifier: Operating System :: OS Independent
Requires-Python: >=3.12
License-File: LICENSE
Requires-Dist: dashscope>=1.19.1
Requires-Dist: elasticsearch>=8.14.0
Requires-Dist: fastapi>=0.115.13
Requires-Dist: fastmcp>=2.10.6
Requires-Dist: loguru>=0.7.3
Requires-Dist: mcp>=1.9.4
Requires-Dist: numpy>=2.3.0
Requires-Dist: openai>=1.88.0
Requires-Dist: pydantic>=2.11.7
Requires-Dist: PyYAML>=6.0.2
Requires-Dist: Requests>=2.32.4
Requires-Dist: uvicorn>=0.34.3
Requires-Dist: setuptools>=75.0
Dynamic: license-file
